rgc_quant/datasets.py
rgc_quant/main.py
rgc_quant/models.py
rgc_quant/utils.py
rgc_quant/models/soma_detection.pth
RGC_Quant-0.0.1.dist-info/LICENSE
RGC_Quant-0.0.1.dist-info/METADATA
RGC_Quant-0.0.1.dist-info/WHEEL
RGC_Quant-0.0.1.dist-info/entry_points.txt
RGC_Quant-0.0.1.dist-info/top_level.txt
RGC_Quant-0.0.1.dist-info/RECORD
